winot/Display.py
winot/DistanceMeter.py
winot/Keypad.py
winot/MotionSensor.py
winot/RemoteWeather.py
winot/WiBuzzer.py
winot/WiKeypad.py
winot/WiLdr.py
winot/WiLed.py
winot/WiMotionSensor.py
winot/WiNoTSwitch.py
winot/WiNoThing.py
winot/WiPushButton.py
winot/WiScale.py
winot/WiWeather.py
winot/__init__.py
winot/__main__.py
winot-0.8.8.dist-info/METADATA
winot-0.8.8.dist-info/WHEEL
winot-0.8.8.dist-info/top_level.txt
winot-0.8.8.dist-info/RECORD
