Metadata-Version: 2.1
Name: winot
Version: 0.8.8
Summary: WiNoT Wrappers
Home-page: https://www.qantom.com/winot_trainer.html
Author: Qantom Software Private Limited
Author-email: info@qantom.com
License: GNU General Public License v3 (GPLv3)
Platform: UNKNOWN
Classifier: Programming Language :: Python :: 2.7
Classifier: License :: OSI Approved :: GNU General Public License v3 (GPLv3)
Classifier: Operating System :: OS Independent
